pngme/api/__init__.py
pngme/api/cache.py
pngme/api/client.py
pngme/api/core.py
pngme/api/encoders.py
pngme/api/errors.py
pngme/api/py.typed
pngme/api/resources/__init__.py
pngme/api/resources/alerts.py
pngme/api/resources/balances.py
pngme/api/resources/institutions.py
pngme/api/resources/transactions.py
pngme/api/resources/users.py
pngme/api/retry.py
pngme_api-0.14.0.dist-info/METADATA
pngme_api-0.14.0.dist-info/LICENSE
pngme_api-0.14.0.dist-info/WHEEL
pngme_api-0.14.0.dist-info/RECORD
