Metadata-Version: 2.1
Name: pngme-api
Version: 0.14.0
Summary: API client used to access Pngme's financial data APIs.
Home-page: https://developers.api.pngme.com/reference/
License: MIT
Author: Ben Fasoli
Author-email: ben@pngme.com
Requires-Python: >=3.8,<4.0
Classifier: License :: OSI Approved :: MIT License
Classifier: Programming Language :: Python :: 3
Classifier: Programming Language :: Python :: 3.8
Classifier: Programming Language :: Python :: 3.9
Classifier: Programming Language :: Python :: 3.10
Classifier: Programming Language :: Python :: 3.11
Requires-Dist: httpx (>=0.22.0,<0.23.0)
Requires-Dist: nest-asyncio (>=1.5.4,<2.0.0)
Requires-Dist: pydantic (>=1.9.0,<2.0.0)
Project-URL: Repository, https://github.com/pngme/pngme-api
